advisor/__init__.py
advisor/bench_runner.py
advisor/config_optimizer_example.py
advisor/db_bench_runner.py
advisor/db_config_optimizer.py
advisor/db_log_parser.py
advisor/db_options_parser.py
advisor/db_stats_fetcher.py
advisor/db_timeseries_parser.py
advisor/ini_parser.py
advisor/rule_parser.py
advisor/rule_parser_example.py
tests/__init__.py
tests/test_db_bench_runner.py
tests/test_db_log_parser.py
tests/test_db_options_parser.py
tests/test_db_stats_fetcher.py
tests/test_rule_parser.py
Adviser_Rocksdb-0.0.1.dist-info/LICENSE
Adviser_Rocksdb-0.0.1.dist-info/METADATA
Adviser_Rocksdb-0.0.1.dist-info/WHEEL
Adviser_Rocksdb-0.0.1.dist-info/top_level.txt
Adviser_Rocksdb-0.0.1.dist-info/RECORD
