Metadata-Version: 2.1
Name: Adviser-Rocksdb
Version: 0.0.1
Summary: Rocksdb's log analyzer
Home-page: https://github.com/BaronStack/Rocksdb-Adviser.git
Author: Example Author
Author-email: author@example.com
License: UNKNOWN
Project-URL: Bug Tracker, https://github.com/BaronStack/Rocksdb-Adviser/issues
Platform: UNKNOWN
Classifier: Programming Language :: Python :: 3
Classifier: License :: OSI Approved :: MIT License
Classifier: Operating System :: OS Independent
Requires-Python: >=3.6
